{
 "absolute_value": 0,
 "align_labels_right": 0,
 "creation": "2023-06-16 00:44:38.894877",
 "custom_format": 1,
 "default_print_language": "uk",
 "disabled": 0,
 "doc_type": "Med Incoming",
 "docstatus": 0,
 "doctype": "Print Format",
 "font_size": 12,
 "format_data": "{\"header\":\"<div class=\\\"document-header\\\">\\n\\t<h3>\u041d\u0410\u041a\u041b\u0410\u0414\u041d\u0410</h3>\\n\\t<p>{{ doc.name }}</p>\\n</div>\",\"sections\":[{\"label\":\"\",\"columns\":[{\"label\":\"\",\"fields\":[{\"label\":\"\u0414\u0430\u0442\u0430\",\"fieldname\":\"date\",\"fieldtype\":\"Date\"}]},{\"label\":\"\",\"fields\":[{\"label\":\"\u041f\u043e\u0441\u0442\u0430\u0447\u0430\u043b\u044c\u043d\u0438\u043a\",\"fieldname\":\"provider\",\"fieldtype\":\"Link\",\"options\":\"Med Enterprise\"}]},{\"label\":\"\",\"fields\":[{\"label\":\"\u041e\u0442\u0440\u0438\u043c\u0443\u0432\u0430\u0447\",\"fieldname\":\"reciver\",\"fieldtype\":\"Link\",\"options\":\"Med Enterprise\"}]}],\"has_fields\":true},{\"label\":\"\",\"columns\":[{\"label\":\"\u0414\u043e\u043a\u0443\u043c\u0435\u043d\u0442 / \u041d\u0430\u043a\u043b\u0430\u0434\u043a\u0430\",\"fields\":[{\"label\":\"\u041d\u043e\u043c\u0435\u0440\",\"fieldname\":\"doc_number\",\"fieldtype\":\"Data\"},{\"label\":\"\u0414\u0430\u0442\u0430\",\"fieldname\":\"doc_data\",\"fieldtype\":\"Date\"}]},{\"label\":\"\u041f\u0456\u0434\u0441\u0442\u0430\u0432\u0430 / \u0414\u043e\u0433\u043e\u0432\u0456\u0440\",\"fields\":[{\"label\":\"\u041d\u0430\u0437\u0432\u0430\",\"fieldname\":\"contract_name\",\"fieldtype\":\"Data\"},{\"label\":\"\u041d\u043e\u043c\u0435\u0440\",\"fieldname\":\"contract_number\",\"fieldtype\":\"Data\"},{\"label\":\"\u0414\u0430\u0442\u0430\",\"fieldname\":\"contract_date\",\"fieldtype\":\"Date\"}]}],\"has_fields\":true},{\"label\":\"\",\"columns\":[{\"label\":\"\",\"fields\":[{\"label\":\"\u041c\u0412\u041e / \u041f\u0435\u0440\u0435\u0434\u0430\u0432\",\"fieldname\":\"transfer_by\",\"fieldtype\":\"Link\",\"options\":\"Med Enterprise User\"}]}],\"has_fields\":true},{\"label\":\"\",\"columns\":[{\"label\":\"\",\"fields\":[{\"label\":\"\u041f\u0435\u0440\u0435\u043b\u0456\u043a\",\"fieldname\":\"incoming\",\"fieldtype\":\"Table\",\"options\":\"Med Incoming Table\",\"table_columns\":[{\"label\":\"\u041d\u0430\u0437\u0432\u0430\",\"fieldname\":\"title\",\"fieldtype\":\"Link\",\"options\":\"Med Incoming Name\",\"width\":10},{\"label\":\"\u041c\u041d\u041d\",\"fieldname\":\"inter_name\",\"fieldtype\":\"Data\",\"width\":10},{\"label\":\"\u041e\u0434. \u0432\u0438\u043c\u0456\u0440\u0443\",\"fieldname\":\"unit\",\"fieldtype\":\"Link\",\"options\":\"Med Incoming Unit\",\"width\":10},{\"label\":\"\u041a\u0456\u043b-\u0442\u044c\",\"fieldname\":\"count\",\"fieldtype\":\"Float\",\"width\":10},{\"label\":\"\u0426\u0456\u043d\u0430\",\"fieldname\":\"coast\",\"fieldtype\":\"Currency\",\"width\":10},{\"label\":\"\u0421\u0443\u043c\u0430\",\"fieldname\":\"sum\",\"fieldtype\":\"Currency\",\"width\":10},{\"label\":\"\u041f\u0414\u0412\",\"fieldname\":\"vat\",\"fieldtype\":\"Currency\",\"width\":10},{\"label\":\"\u0412\u0441\u044c\u043e\u0433\u043e\",\"fieldname\":\"total\",\"fieldtype\":\"Currency\",\"width\":10}]}]}],\"has_fields\":true}]}",
 "html": "<h3 class=\"center\" style=\"text-align: center;\">\u041d\u0410\u041a\u041b\u0410\u0414\u041d\u0410</h3>\r\n<div style=\"text-align: center;\">\u2116 {{ doc.doc_number }} \u0432\u0456\u0434 {{ doc.doc_data }}</div>\r\n<div>&nbsp;</div>\r\n<div><strong>\u041f\u043e\u0441\u0442\u0430\u0447\u0430\u043b\u044c\u043d\u0438\u043a</strong> {{ frappe.db.get_value(\"Med Enterprise\", doc.provider, \"full_name\") }}</div>\r\n<div><strong>\u0415\u0414\u0420\u041f\u041e\u0423</strong> {{ frappe.db.get_value(\"Med Enterprise\", doc.provider, \"edrpou\") }}</div>\r\n<div><strong>\u042e\u0440\u0438\u0434\u0438\u0447\u043d\u0430 \u0430\u0434\u0440\u0435\u0441\u0430</strong> {{ frappe.db.get_value(\"Med Enterprise\", doc.provider, \"adress\") }}</div>\r\n<div><strong>\u0427\u0435\u0440\u0435\u0437</strong> {{ frappe.db.get_value(\"Med Enterprise User\", doc.transfer_by, \"full_name\") }}</div>\r\n<div><strong>\u041f\u0456\u0434\u0441\u0442\u0430\u0432\u0430</strong> {{ doc.contract_name }} \u2116{{ doc.contract_number }} \u0432\u0456\u0434 {{doc.contract_date }}</div>\r\n<div>&nbsp;</div>\r\n<div><strong>\u041e\u0442\u0440\u0438\u043c\u0443\u0432\u0430\u0447</strong> {{ frappe.db.get_value(\"Med Enterprise\", doc.reciver, \"full_name\") }}</div>\r\n<div><strong>\u0415\u0414\u0420\u041f\u041e\u0423</strong> {{ frappe.db.get_value(\"Med Enterprise\", doc.reciver, \"edrpou\") }}</div>\r\n<div><strong>\u042e\u0440\u0438\u0434\u0438\u0447\u043d\u0430 \u0430\u0434\u0440\u0435\u0441\u0430</strong> {{ frappe.db.get_value(\"Med Enterprise\", doc.reciver, \"adress\") }}</div>\r\n<div><strong>\u0427\u0435\u0440\u0435\u0437</strong> {{ frappe.db.get_value(\"Med Enterprise User\", doc.recive_by, \"full_name\") }}</div>\r\n\r\n<div></div>\r\n<table class=\"table table-bordered\">\r\n\t<tbody>\r\n\t\t<tr>\r\n\t\t\t<th>\u2116 \u0437/\u043f</th>\r\n\t\t\t<th>\u041d\u0430\u0437\u0432\u0430</th>\r\n\t\t\t<th>\u041c\u041d\u041d</th>\r\n\t\t\t<th class=\"text-right\">\u041e\u0434. \u0432\u0438\u043c\u0456\u0440\u0443</th>\r\n\t\t\t<th class=\"text-right\">\u041a-\u0442\u044c</th>\r\n\t\t\t<th class=\"text-right\">\u0426\u0456\u043d\u0430 \u0437\u0430 \u043e\u0434\u0438\u043d\u0438\u0446\u044e, \u0433\u0440\u043d.</th>\r\n\t\t\t<th class=\"text-right\">\u0421\u0443\u043c\u0430, \u0433\u0440\u043d</th>\r\n\t\t\t<th class=\"text-right\">\u041f\u0414\u0412</th>\r\n\t\t\t<th class=\"text-right\">\u0412\u0441\u044c\u043e\u0433\u043e \u0441\u0443\u043c\u0430, \u0433\u0440\u043d.</th>\r\n\t\t</tr>\r\n\t\t{%- for row in doc.incoming -%}\r\n\t\t<tr>\r\n\t\t\t<td>{{ row.idx }}</td>\r\n\t\t\t<td>\r\n\t\t\t\t{{ row.title }}\r\n\t\t\t</td>\r\n\t\t\t<td>{{ row.inter_name }}</td>\r\n\t\t\t<td style=\"text-align: right;\">{{ row.unit }}</td>\r\n\t\t\t<td style=\"text-align: right;\">{{ row.count }}</td>\r\n\t\t\t<td style=\"text-align: right;\">{{ row.coast }}</td>\r\n\t\t\t<td style=\"text-align: right;\">{{ row.sum }}</td>\r\n\t\t\t<td style=\"text-align: right;\">{{ row.vat }}</td>\r\n\t\t\t<td style=\"text-align: right;\">{{ row.total }}</td>\r\n\t\t</tr>\r\n\t\t{%- endfor -%}\r\n\t</tbody>\r\n</table>\r\n<div>&nbsp;</div>\r\n\r\n\r\n<table>\r\n\t<tbody>\r\n\t\t<tr>\r\n\t\t\t<td width=\"50%\">\r\n\t\t\t\t<p>\u041f\u0435\u0440\u0435\u0434\u0430\u0432</p>\r\n\t\t\t</td>\r\n\t\t\t<td width=\"50%\">\r\n\t\t\t\t<p>\u041f\u0440\u0438\u0439\u043d\u044f\u0432</p>\r\n\t\t\t</td>\r\n\t\t</tr>\r\n\t\t<tr>\r\n\t\t\t<td width=\"50%\">\r\n\t\t\t\t<p>{{ frappe.db.get_value(\"Med Enterprise\", doc.provider, \"full_name\") }}</p>\r\n\t\t\t</td>\r\n\t\t\t<td width=\"50%\">\r\n\t\t\t\t<p>{{ frappe.db.get_value(\"Med Enterprise\", doc.reciver, \"full_name\") }}</p>\r\n\t\t\t</td>\r\n\t\t</tr>\r\n\t\t<tr>\r\n\t\t\t<td width=\"50%\">\r\n\t\t\t\t<p><u>{{ frappe.db.get_value(\"Med Enterprise User\", doc.transfer_by, \"full_name\") }}</u></p>\r\n\t\t\t</td>\r\n\t\t\t<td width=\"50%\">\r\n\t\t\t\t<p><u>{{ frappe.db.get_value(\"Med Enterprise User\", doc.recive_by, \"full_name\") }}</u></p>\r\n\t\t\t</td>\r\n\t\t</tr>\r\n\t</tbody>\r\n</table>",
 "idx": 0,
 "line_breaks": 0,
 "margin_bottom": 15.0,
 "margin_left": 15.0,
 "margin_right": 15.0,
 "margin_top": 15.0,
 "modified": "2023-06-17 00:15:19.601121",
 "modified_by": "Administrator",
 "module": "Medical",
 "name": "\u041d\u0430\u043a\u043b\u0430\u0434\u043d\u0430",
 "owner": "Administrator",
 "page_number": "Hide",
 "print_format_builder": 0,
 "print_format_builder_beta": 1,
 "print_format_type": "Jinja",
 "raw_printing": 0,
 "show_section_headings": 0,
 "standard": "Yes"
}